lammps_ast/__init__.py
lammps_ast/comparator.py
lammps_ast/error_handler.py
lammps_ast/parser.py
lammps_ast/sanitizer.py
lammps_ast/transformer.py
lammps_ast/grammar/lammps_grammar.lark
lammps_ast-0.1.7.dist-info/METADATA
lammps_ast-0.1.7.dist-info/WHEEL
lammps_ast-0.1.7.dist-info/entry_points.txt
lammps_ast-0.1.7.dist-info/top_level.txt
lammps_ast-0.1.7.dist-info/RECORD
