Metadata-Version: 2.4
Name: lammps_ast
Version: 0.1.7
Summary: A LAMMPS script parser and sanitizer using Lark
Home-page: https://github.com/ethanholbrook/LAMMPS-AST
Author: Juan C. Verduzco, Ethan W. Holbrook
Author-email: holbrooe@purdue.edu
Classifier: Programming Language :: Python :: 3
Classifier: License :: OSI Approved :: MIT License
Classifier: Operating System :: OS Independent
Classifier: Topic :: Scientific/Engineering :: Chemistry
Classifier: Intended Audience :: Science/Research
Requires-Python: >=3.10
Requires-Dist: lark-parser>=0.12.0
Requires-Dist: colorama
Requires-Dist: graphviz
Requires-Dist: zss
Requires-Dist: pydot
Requires-Dist: simpleeval
Dynamic: author
Dynamic: author-email
Dynamic: classifier
Dynamic: description
Dynamic: description-content-type
Dynamic: home-page
Dynamic: requires-dist
Dynamic: requires-python
Dynamic: summary
